Compiled from "RaidCrystalBlockEntity.java"
public abstract class com.necro.raid.dens.common.blocks.entity.RaidCrystalBlockEntity extends net.minecraft.world.level.block.entity.BlockEntity implements software.bernie.geckolib.animatable.GeoBlockEntity {
  private int clears;

  private int inactiveTicks;

  private int soundTicks;

  private int beamHeight;

  private int lastCheckedY;

  private int checkingHeight;

  private java.util.UUID uuid;

  private net.minecraft.resources.ResourceLocation raidBucket;

  private net.minecraft.resources.ResourceLocation raidBoss;

  private com.necro.raid.dens.common.data.raid.RaidResetContext lastReset;

  private boolean isOpen;

  private java.util.Set<java.lang.String> aspects;

  private java.util.function.Consumer<net.minecraft.server.level.ServerPlayer> aspectSync;

  private final software.bernie.geckolib.animatable.instance.AnimatableInstanceCache cache;

  public com.necro.raid.dens.common.blocks.entity.RaidCrystalBlockEntity(net.minecraft.world.level.block.entity.BlockEntityType<? extends com.necro.raid.dens.common.blocks.entity.RaidCrystalBlockEntity>, net.minecraft.core.BlockPos, net.minecraft.world.level.block.state.BlockState);
    Code:
       0: aload_0
       1: aload_1
       2: aload_2
       3: aload_3
       4: invokespecial #69                 // Method net/minecraft/world/level/block/entity/BlockEntity."<init>":(Lnet/minecraft/world/level/block/entity/BlockEntityType;Lnet/minecraft/core/BlockPos;Lnet/minecraft/world/level/block/state/BlockState;)V
       7: aload_0
       8: aload_0
       9: invokestatic  #75                 // Method software/bernie/geckolib/util/GeckoLibUtil.createInstanceCache:(Lsoftware/bernie/geckolib/animatable/GeoAnimatable;)Lsoftware/bernie/geckolib/animatable/instance/AnimatableInstanceCache;
      12: putfield      #77                 // Field cache:Lsoftware/bernie/geckolib/animatable/instance/AnimatableInstanceCache;
      15: aload_0
      16: iconst_0
      17: putfield      #79                 // Field soundTicks:I
      20: aload_0
      21: iconst_0
      22: putfield      #81                 // Field beamHeight:I
      25: aload_0
      26: iconst_m1
      27: putfield      #83                 // Field lastCheckedY:I
      30: aload_0
      31: iconst_0
      32: putfield      #85                 // Field checkingHeight:I
      35: aload_0
      36: invokestatic  #91                 // Method java/util/UUID.randomUUID:()Ljava/util/UUID;
      39: putfield      #93                 // Field uuid:Ljava/util/UUID;
      42: aload_0
      43: iconst_0
      44: putfield      #95                 // Field isOpen:Z
      47: return

  public void tick(net.minecraft.world.level.Level, net.minecraft.core.BlockPos, net.minecraft.world.level.block.state.BlockState);
    Code:
       0: aload_1
       1: invokevirtual #110                // Method net/minecraft/world/level/Level.isClientSide:()Z
       4: ifeq          13
       7: aload_0
       8: aload_3
       9: invokevirtual #114                // Method clientTick:(Lnet/minecraft/world/level/block/state/BlockState;)V
      12: return
      13: aload_0
      14: invokevirtual #117                // Method isIdle:()Z
      17: istore        4
      19: aload_0
      20: invokevirtual #120                // Method getUuid:()Ljava/util/UUID;
      23: invokestatic  #126                // Method com/necro/raid/dens/common/raids/helpers/RaidHelper.hasRaidState:(Ljava/util/UUID;)Z
      26: ifeq          38
      29: iload         4
      31: ifeq          38
      34: aload_0
      35: invokevirtual #130                // Method closeRaid:()V
      38: aload_0
      39: aload_3
      40: invokevirtual #134                // Method canGenerateBoss:(Lnet/minecraft/world/level/block/state/BlockState;)Z
      43: ifeq          70
      46: aload_0
      47: getfield      #136                // Field raidBoss:Lnet/minecraft/resources/ResourceLocation;
      50: ifnull        63
      53: aload_0
      54: getfield      #136                // Field raidBoss:Lnet/minecraft/resources/ResourceLocation;
      57: invokestatic  #142                // Method com/necro/raid/dens/common/registry/RaidRegistry.exists:(Lnet/minecraft/resources/ResourceLocation;)Z
      60: ifne          70
      63: aload_0
      64: aload_1
      65: aload_2
      66: aload_3
      67: invokevirtual #145                // Method generateRaidBoss:(Lnet/minecraft/world/level/Level;Lnet/minecraft/core/BlockPos;Lnet/minecraft/world/level/block/state/BlockState;)V
      70: aload_0
      71: invokevirtual #148                // Method isInProgress:()Z
      74: ifeq          106
      77: iload         4
      79: ifeq          106
      82: aload_0
      83: dup
      84: getfield      #150                // Field inactiveTicks:I
      87: iconst_1
      88: iadd
      89: dup_x1
      90: putfield      #150                // Field inactiveTicks:I
      93: sipush        2400
      96: if_icmple     111
      99: aload_0
     100: invokevirtual #130                // Method closeRaid:()V
     103: goto          111
     106: aload_0
     107: iconst_0
     108: putfield      #150                // Field inactiveTicks:I
     111: aload_0
     112: aload_3
     113: invokevirtual #153                // Method isActive:(Lnet/minecraft/world/level/block/state/BlockState;)Z
     116: ifeq          156
     119: aload_0
     120: dup
     121: getfield      #79                 // Field soundTicks:I
     124: iconst_1
     125: iadd
     126: dup_x1
     127: putfield      #79                 // Field soundTicks:I
     130: bipush        120
     132: irem
     133: ifne          156
     136: aload_1
     137: aconst_null
     138: aload_2
     139: getstatic     #159                // Field net/minecraft/sounds/SoundEvents.AMETHYST_BLOCK_CHIME:Lnet/minecraft/sounds/SoundEvent;
     142: getstatic     #165                // Field net/minecraft/sounds/SoundSource.BLOCKS:Lnet/minecraft/sounds/SoundSource;
     145: ldc           #166                // float 0.5f
     147: fconst_1
     148: invokevirtual #170                // Method net/minecraft/world/level/Level.playSound:(Lnet/minecraft/world/entity/player/Player;Lnet/minecraft/core/BlockPos;Lnet/minecraft/sounds/SoundEvent;Lnet/minecraft/sounds/SoundSource;FF)V
     151: aload_0
     152: iconst_0
     153: putfield      #79                 // Field soundTicks:I
     156: aload_3
     157: getstatic     #176                // Field com/necro/raid/dens/common/blocks/block/RaidCrystalBlock.CAN_RESET:Lnet/minecraft/world/level/block/state/properties/BooleanProperty;
     160: invokevirtual #182                // Method net/minecraft/world/level/block/state/BlockState.getValue:(Lnet/minecraft/world/level/block/state/properties/Property;)Ljava/lang/Comparable;
     163: checkcast     #184                // class java/lang/Boolean
     166: invokevirtual #187                // Method java/lang/Boolean.booleanValue:()Z
     169: ifne          173
     172: return
     173: getstatic     #193                // Field com/necro/raid/dens/common/CobblemonRaidDens.CONFIG:Lcom/necro/raid/dens/common/config/RaidConfig;
     176: getfield      #198                // Field com/necro/raid/dens/common/config/RaidConfig.reset_time:I
     179: ifgt          183
     182: return
     183: aload_0
     184: invokevirtual #148                // Method isInProgress:()Z
     187: ifeq          191
     190: return
     191: aload_1
     192: invokevirtual #202                // Method net/minecraft/world/level/Level.getGameTime:()J
     195: lstore        5
     197: aload_0
     198: getfield      #204                // Field lastReset:Lcom/necro/raid/dens/common/data/raid/RaidResetContext;
     201: ifnonnull     220
     204: aload_0
     205: new           #206                // class com/necro/raid/dens/common/data/raid/RaidResetContext
     208: dup
     209: lload         5
     211: invokespecial #209                // Method com/necro/raid/dens/common/data/raid/RaidResetContext."<init>":(J)V
     214: putfield      #204                // Field lastReset:Lcom/necro/raid/dens/common/data/raid/RaidResetContext;
     217: goto          239
     220: aload_0
     221: getfield      #204                // Field lastReset:Lcom/necro/raid/dens/common/data/raid/RaidResetContext;
     224: lload         5
     226: invokevirtual #213                // Method com/necro/raid/dens/common/data/raid/RaidResetContext.shouldReset:(J)Z
     229: ifeq          239
     232: aload_0
     233: aload_1
     234: aload_2
     235: aload_3
     236: invokevirtual #145                // Method generateRaidBoss:(Lnet/minecraft/world/level/Level;Lnet/minecraft/core/BlockPos;Lnet/minecraft/world/level/block/state/BlockState;)V
     239: return

  private void clientTick(net.minecraft.world.level.block.state.BlockState);
    Code:
       0: aload_0
       1: aload_1
       2: invokevirtual #153                // Method isActive:(Lnet/minecraft/world/level/block/state/BlockState;)Z
       5: ifne          9
       8: return
       9: aload_0
      10: aload_0
      11: invokevirtual #220                // Method getLevel:()Lnet/minecraft/world/level/Level;
      14: invokevirtual #224                // Method calculateBeamHeight:(Lnet/minecraft/world/level/Level;)V
      17: return

  private void calculateBeamHeight(net.minecraft.world.level.Level);
    Code:
       0: aload_0
       1: invokevirtual #228                // Method getBlockPos:()Lnet/minecraft/core/BlockPos;
       4: astore_2
       5: sipush        320
       8: aload_2
       9: invokevirtual #232                // Method net/minecraft/core/BlockPos.getY:()I
      12: isub
      13: istore_3
      14: aload_1
      15: aload_2
      16: invokestatic  #238                // Method com/necro/raid/dens/common/util/RaidUtils.hasSkyAccess:(Lnet/minecraft/world/level/LevelReader;Lnet/minecraft/core/BlockPos;)Z
      19: istore        4
      21: iload         4
      23: ifne          162
      26: aload_0
      27: getfield      #83                 // Field lastCheckedY:I
      30: aload_2
      31: invokevirtual #232                // Method net/minecraft/core/BlockPos.getY:()I
      34: if_icmpge     50
      37: aload_0
      38: aload_2
      39: invokevirtual #232                // Method net/minecraft/core/BlockPos.getY:()I
      42: putfield      #83                 // Field lastCheckedY:I
      45: aload_0
      46: iconst_0
      47: putfield      #85                 // Field checkingHeight:I
      50: new           #11                 // class net/minecraft/core/BlockPos$MutableBlockPos
      53: dup
      54: aload_2
      55: invokevirtual #241                // Method net/minecraft/core/BlockPos.getX:()I
      58: aload_0
      59: getfield      #83                 // Field lastCheckedY:I
      62: iconst_1
      63: iadd
      64: aload_2
      65: invokevirtual #244                // Method net/minecraft/core/BlockPos.getZ:()I
      68: invokespecial #247                // Method net/minecraft/core/BlockPos$MutableBlockPos."<init>":(III)V
      71: astore        5
      73: iconst_0
      74: istore        6
      76: iload         6
      78: bipush        10
      80: if_icmpge     162
      83: aload_0
      84: getfield      #85                 // Field checkingHeight:I
      87: iload_3
      88: if_icmpge     162
      91: aload_1
      92: aload         5
      94: invokevirtual #251                // Method net/minecraft/world/level/Level.getBlockState:(Lnet/minecraft/core/BlockPos;)Lnet/minecraft/world/level/block/state/BlockState;
      97: aload_1
      98: aload         5
     100: invokevirtual #255                // Method net/minecraft/world/level/block/state/BlockState.getLightBlock:(Lnet/minecraft/world/level/BlockGetter;Lnet/minecraft/core/BlockPos;)I
     103: bipush        15
     105: if_icmplt     127
     108: aload_0
     109: aload_0
     110: getfield      #85                 // Field checkingHeight:I
     113: putfield      #81                 // Field beamHeight:I
     116: aload_0
     117: aload_2
     118: invokevirtual #232                // Method net/minecraft/core/BlockPos.getY:()I
     121: iconst_1
     122: isub
     123: putfield      #83                 // Field lastCheckedY:I
     126: return
     127: aload_0
     128: dup
     129: getfield      #85                 // Field checkingHeight:I
     132: iconst_1
     133: iadd
     134: putfield      #85                 // Field checkingHeight:I
     137: aload_0
     138: dup
     139: getfield      #83                 // Field lastCheckedY:I
     142: iconst_1
     143: iadd
     144: putfield      #83                 // Field lastCheckedY:I
     147: aload         5
     149: iconst_0
     150: iconst_1
     151: iconst_0
     152: invokevirtual #259                // Method net/minecraft/core/BlockPos$MutableBlockPos.move:(III)Lnet/minecraft/core/BlockPos$MutableBlockPos;
     155: pop
     156: iinc          6, 1
     159: goto          76
     162: iload         4
     164: ifne          175
     167: aload_0
     168: getfield      #85                 // Field checkingHeight:I
     171: iload_3
     172: if_icmplt     199
     175: aload_0
     176: iload_3
     177: sipush        192
     180: iadd
     181: putfield      #81                 // Field beamHeight:I
     184: aload_0
     185: aload_2
     186: invokevirtual #232                // Method net/minecraft/core/BlockPos.getY:()I
     189: iconst_1
     190: isub
     191: putfield      #83                 // Field lastCheckedY:I
     194: aload_0
     195: iconst_0
     196: putfield      #85                 // Field checkingHeight:I
     199: return

  public int getBeamHeight();
    Code:
       0: aload_0
       1: getfield      #81                 // Field beamHeight:I
       4: ireturn

  public void generateRaidBoss(net.minecraft.world.level.Level, net.minecraft.core.BlockPos, net.minecraft.world.level.block.state.BlockState);
    Code:
       0: aload_3
       1: getstatic     #268                // Field com/necro/raid/dens/common/blocks/block/RaidCrystalBlock.CYCLE_MODE:Lnet/minecraft/world/level/block/state/properties/EnumProperty;
       4: invokevirtual #182                // Method net/minecraft/world/level/block/state/BlockState.getValue:(Lnet/minecraft/world/level/block/state/properties/Property;)Ljava/lang/Comparable;
       7: checkcast     #270                // class com/necro/raid/dens/common/data/raid/RaidCycleMode
      10: astore        4
      12: aload         4
      14: getstatic     #273                // Field com/necro/raid/dens/common/data/raid/RaidCycleMode.CONFIG:Lcom/necro/raid/dens/common/data/raid/RaidCycleMode;
      17: if_acmpne     28
      20: getstatic     #193                // Field com/necro/raid/dens/common/CobblemonRaidDens.CONFIG:Lcom/necro/raid/dens/common/config/RaidConfig;
      23: getfield      #276                // Field com/necro/raid/dens/common/config/RaidConfig.cycle_mode:Lcom/necro/raid/dens/common/data/raid/RaidCycleMode;
      26: astore        4
      28: getstatic     #280                // Field com/necro/raid/dens/common/blocks/entity/RaidCrystalBlockEntity$1.$SwitchMap$com$necro$raid$dens$common$data$raid$RaidCycleMode:[I
      31: aload         4
      33: invokevirtual #283                // Method com/necro/raid/dens/common/data/raid/RaidCycleMode.ordinal:()I
      36: iaload
      37: lookupswitch  { // 2

                     1: 64

                     2: 75
               default: 86
          }
      64: aload_0
      65: aload_1
      66: aload_3
      67: aload         4
      69: invokevirtual #287                // Method generateFromExisting:(Lnet/minecraft/world/level/Level;Lnet/minecraft/world/level/block/state/BlockState;Lcom/necro/raid/dens/common/data/raid/RaidCycleMode;)Lnet/minecraft/resources/ResourceLocation;
      72: goto          94
      75: aload_0
      76: aload_1
      77: aload_3
      78: aload         4
      80: invokevirtual #290                // Method generateFromBucket:(Lnet/minecraft/world/level/Level;Lnet/minecraft/world/level/block/state/BlockState;Lcom/necro/raid/dens/common/data/raid/RaidCycleMode;)Lnet/minecraft/resources/ResourceLocation;
      83: goto          94
      86: aload_0
      87: aload_1
      88: aload_3
      89: aload         4
      91: invokevirtual #293                // Method generateRandom:(Lnet/minecraft/world/level/Level;Lnet/minecraft/world/level/block/state/BlockState;Lcom/necro/raid/dens/common/data/raid/RaidCycleMode;)Lnet/minecraft/resources/ResourceLocation;
      94: astore        5
      96: aload         5
      98: invokestatic  #299                // Method com/necro/raid/dens/common/registry/RaidRegistry.getRaidBoss:(Lnet/minecraft/resources/ResourceLocation;)Lcom/necro/raid/dens/common/data/raid/RaidBoss;
     101: astore        6
     103: aload         6
     105: ifnonnull     109
     108: return
     109: new           #303                // class com/necro/raid/dens/common/events/SetRaidBossEvent
     112: dup
     113: aload         6
     115: invokespecial #306                // Method com/necro/raid/dens/common/events/SetRaidBossEvent."<init>":(Lcom/necro/raid/dens/common/data/raid/RaidBoss;)V
     118: astore        7
     120: getstatic     #312                // Field com/necro/raid/dens/common/events/RaidEvents.SET_RAID_BOSS:Lcom/cobblemon/mod/common/api/reactive/SimpleObservable;
     123: iconst_1
     124: anewarray     #303                // class com/necro/raid/dens/common/events/SetRaidBossEvent
     127: dup
     128: iconst_0
     129: aload         7
     131: aastore
     132: invokevirtual #318                // Method com/cobblemon/mod/common/api/reactive/SimpleObservable.emit:([Ljava/lang/Object;)V
     135: aload         7
     137: invokevirtual #321                // Method com/necro/raid/dens/common/events/SetRaidBossEvent.getRaidBoss:()Lcom/necro/raid/dens/common/data/raid/RaidBoss;
     140: astore        6
     142: aload         6
     144: ifnonnull     168
     147: aload_0
     148: iconst_0
     149: putfield      #150                // Field inactiveTicks:I
     152: aload_0
     153: new           #206                // class com/necro/raid/dens/common/data/raid/RaidResetContext
     156: dup
     157: aload_1
     158: invokevirtual #202                // Method net/minecraft/world/level/Level.getGameTime:()J
     161: invokespecial #209                // Method com/necro/raid/dens/common/data/raid/RaidResetContext."<init>":(J)V
     164: putfield      #204                // Field lastReset:Lcom/necro/raid/dens/common/data/raid/RaidResetContext;
     167: return
     168: aload_0
     169: aload         6
     171: invokevirtual #325                // Method com/necro/raid/dens/common/data/raid/RaidBoss.getId:()Lnet/minecraft/resources/ResourceLocation;
     174: aload_1
     175: invokevirtual #202                // Method net/minecraft/world/level/Level.getGameTime:()J
     178: invokevirtual #329                // Method setRaidBoss:(Lnet/minecraft/resources/ResourceLocation;J)V
     181: aload_1
     182: aload_2
     183: aload_3
     184: getstatic     #332                // Field com/necro/raid/dens/common/blocks/block/RaidCrystalBlock.RAID_TIER:Lnet/minecraft/world/level/block/state/properties/EnumProperty;
     187: aload         6
     189: invokevirtual #336                // Method com/necro/raid/dens/common/data/raid/RaidBoss.getTier:()Lcom/necro/raid/dens/common/data/raid/RaidTier;
     192: invokevirtual #340                // Method net/minecraft/world/level/block/state/BlockState.setValue:(Lnet/minecraft/world/level/block/state/properties/Property;Ljava/lang/Comparable;)Ljava/lang/Object;
     195: checkcast     #178                // class net/minecraft/world/level/block/state/BlockState
     198: getstatic     #343                // Field com/necro/raid/dens/common/blocks/block/RaidCrystalBlock.RAID_TYPE:Lnet/minecraft/world/level/block/state/properties/EnumProperty;
     201: aload         6
     203: invokevirtual #347                // Method com/necro/raid/dens/common/data/raid/RaidBoss.getType:()Lcom/necro/raid/dens/common/data/raid/RaidType;
     206: invokevirtual #340                // Method net/minecraft/world/level/block/state/BlockState.setValue:(Lnet/minecraft/world/level/block/state/properties/Property;Ljava/lang/Comparable;)Ljava/lang/Object;
     209: checkcast     #178                // class net/minecraft/world/level/block/state/BlockState
     212: getstatic     #350                // Field com/necro/raid/dens/common/blocks/block/RaidCrystalBlock.ACTIVE:Lnet/minecraft/world/level/block/state/properties/BooleanProperty;
     215: iconst_1
     216: invokestatic  #354                // Method java/lang/Boolean.valueOf:(Z)Ljava/lang/Boolean;
     219: invokevirtual #340                // Method net/minecraft/world/level/block/state/BlockState.setValue:(Lnet/minecraft/world/level/block/state/properties/Property;Ljava/lang/Comparable;)Ljava/lang/Object;
     222: checkcast     #178                // class net/minecraft/world/level/block/state/BlockState
     225: iconst_2
     226: invokevirtual #358                // Method net/minecraft/world/level/Level.setBlock:(Lnet/minecraft/core/BlockPos;Lnet/minecraft/world/level/block/state/BlockState;I)Z
     229: pop
     230: getstatic     #361                // Field com/necro/raid/dens/common/events/RaidEvents.RAID_DEN_SPAWN:Lcom/cobblemon/mod/common/api/reactive/SimpleObservable;
     233: iconst_1
     234: anewarray     #363                // class com/necro/raid/dens/common/events/RaidDenSpawnEvent
     237: dup
     238: iconst_0
     239: new           #363                // class com/necro/raid/dens/common/events/RaidDenSpawnEvent
     242: dup
     243: aload_1
     244: checkcast     #365                // class net/minecraft/server/level/ServerLevel
     247: aload_2
     248: aload         6
     250: invokespecial #368                // Method com/necro/raid/dens/common/events/RaidDenSpawnEvent."<init>":(Lnet/minecraft/server/level/ServerLevel;Lnet/minecraft/core/BlockPos;Lcom/necro/raid/dens/common/data/raid/RaidBoss;)V
     253: aastore
     254: invokevirtual #318                // Method com/cobblemon/mod/common/api/reactive/SimpleObservable.emit:([Ljava/lang/Object;)V
     257: return

  private net.minecraft.resources.ResourceLocation generateFromBucket(net.minecraft.world.level.Level, net.minecraft.world.level.block.state.BlockState, com.necro.raid.dens.common.data.raid.RaidCycleMode);
    Code:
       0: aload_0
       1: getfield      #375                // Field raidBucket:Lnet/minecraft/resources/ResourceLocation;
       4: ifnonnull     26
       7: aload_0
       8: aload_1
       9: invokevirtual #379                // Method net/minecraft/world/level/Level.getRandom:()Lnet/minecraft/util/RandomSource;
      12: aload_1
      13: aload_0
      14: invokevirtual #228                // Method getBlockPos:()Lnet/minecraft/core/BlockPos;
      17: invokevirtual #383                // Method net/minecraft/world/level/Level.getBiome:(Lnet/minecraft/core/BlockPos;)Lnet/minecraft/core/Holder;
      20: invokestatic  #389                // Method com/necro/raid/dens/common/registry/RaidBucketRegistry.getRandomBucket:(Lnet/minecraft/util/RandomSource;Lnet/minecraft/core/Holder;)Lnet/minecraft/resources/ResourceLocation;
      23: putfield      #375                // Field raidBucket:Lnet/minecraft/resources/ResourceLocation;
      26: aload_0
      27: getfield      #375                // Field raidBucket:Lnet/minecraft/resources/ResourceLocation;
      30: ifnonnull     41
      33: aload_0
      34: aload_1
      35: aload_2
      36: aload_3
      37: invokevirtual #293                // Method generateRandom:(Lnet/minecraft/world/level/Level;Lnet/minecraft/world/level/block/state/BlockState;Lcom/necro/raid/dens/common/data/raid/RaidCycleMode;)Lnet/minecraft/resources/ResourceLocation;
      40: areturn
      41: aload_0
      42: getfield      #375                // Field raidBucket:Lnet/minecraft/resources/ResourceLocation;
      45: invokestatic  #393                // Method com/necro/raid/dens/common/registry/RaidBucketRegistry.getBucket:(Lnet/minecraft/resources/ResourceLocation;)Lcom/necro/raid/dens/common/data/raid/RaidBucket;
      48: astore        4
      50: aload         4
      52: ifnonnull     68
      55: aload_0
      56: aconst_null
      57: putfield      #375                // Field raidBucket:Lnet/minecraft/resources/ResourceLocation;
      60: aload_0
      61: aload_1
      62: aload_2
      63: aload_3
      64: invokevirtual #290                // Method generateFromBucket:(Lnet/minecraft/world/level/Level;Lnet/minecraft/world/level/block/state/BlockState;Lcom/necro/raid/dens/common/data/raid/RaidCycleMode;)Lnet/minecraft/resources/ResourceLocation;
      67: areturn
      68: aload         4
      70: aload_1
      71: invokevirtual #379                // Method net/minecraft/world/level/Level.getRandom:()Lnet/minecraft/util/RandomSource;
      74: aload_1
      75: invokevirtual #399                // Method com/necro/raid/dens/common/data/raid/RaidBucket.getRandomRaidBoss:(Lnet/minecraft/util/RandomSource;Lnet/minecraft/world/level/Level;)Lnet/minecraft/resources/ResourceLocation;
      78: astore        5
      80: aload         5
      82: ifnonnull     95
      85: aload_0
      86: aload_1
      87: aload_2
      88: aload_3
      89: invokevirtual #293                // Method generateRandom:(Lnet/minecraft/world/level/Level;Lnet/minecraft/world/level/block/state/BlockState;Lcom/necro/raid/dens/common/data/raid/RaidCycleMode;)Lnet/minecraft/resources/ResourceLocation;
      92: goto          97
      95: aload         5
      97: areturn

  private net.minecraft.resources.ResourceLocation generateRandom(net.minecraft.world.level.Level, net.minecraft.world.level.block.state.BlockState, com.necro.raid.dens.common.data.raid.RaidCycleMode);
    Code:
       0: aload_3
       1: invokevirtual #405                // Method com/necro/raid/dens/common/data/raid/RaidCycleMode.canCycleTier:()Z
       4: ifeq          18
       7: aload_1
       8: invokevirtual #379                // Method net/minecraft/world/level/Level.getRandom:()Lnet/minecraft/util/RandomSource;
      11: aload_1
      12: invokestatic  #411                // Method com/necro/raid/dens/common/data/raid/RaidTier.getWeightedRandom:(Lnet/minecraft/util/RandomSource;Lnet/minecraft/world/level/Level;)Lcom/necro/raid/dens/common/data/raid/RaidTier;
      15: goto          28
      18: aload_2
      19: getstatic     #332                // Field com/necro/raid/dens/common/blocks/block/RaidCrystalBlock.RAID_TIER:Lnet/minecraft/world/level/block/state/properties/EnumProperty;
      22: invokevirtual #182                // Method net/minecraft/world/level/block/state/BlockState.getValue:(Lnet/minecraft/world/level/block/state/properties/Property;)Ljava/lang/Comparable;
      25: checkcast     #407                // class com/necro/raid/dens/common/data/raid/RaidTier
      28: astore        4
      30: aload_3
      31: invokevirtual #414                // Method com/necro/raid/dens/common/data/raid/RaidCycleMode.canCycleType:()Z
      34: ifeq          41
      37: aconst_null
      38: goto          51
      41: aload_2
      42: getstatic     #343                // Field com/necro/raid/dens/common/blocks/block/RaidCrystalBlock.RAID_TYPE:Lnet/minecraft/world/level/block/state/properties/EnumProperty;
      45: invokevirtual #182                // Method net/minecraft/world/level/block/state/BlockState.getValue:(Lnet/minecraft/world/level/block/state/properties/Property;)Ljava/lang/Comparable;
      48: checkcast     #416                // class com/necro/raid/dens/common/data/raid/RaidType
      51: astore        5
      53: aload_1
      54: invokevirtual #379                // Method net/minecraft/world/level/Level.getRandom:()Lnet/minecraft/util/RandomSource;
      57: aload_1
      58: aload         4
      60: aload         5
      62: aconst_null
      63: invokestatic  #419                // Method com/necro/raid/dens/common/registry/RaidRegistry.getRandomRaidBoss:(Lnet/minecraft/util/RandomSource;Lnet/minecraft/world/level/Level;Lcom/necro/raid/dens/common/data/raid/RaidTier;Lcom/necro/raid/dens/common/data/raid/RaidType;Ljava/lang/String;)Lnet/minecraft/resources/ResourceLocation;
      66: areturn

  private net.minecraft.resources.ResourceLocation generateFromExisting(net.minecraft.world.level.Level, net.minecraft.world.level.block.state.BlockState, com.necro.raid.dens.common.data.raid.RaidCycleMode);
    Code:
       0: aload_0
       1: getfield      #136                // Field raidBoss:Lnet/minecraft/resources/ResourceLocation;
       4: ifnonnull     17
       7: aload_0
       8: aload_1
       9: aload_2
      10: aload_3
      11: invokevirtual #293                // Method generateRandom:(Lnet/minecraft/world/level/Level;Lnet/minecraft/world/level/block/state/BlockState;Lcom/necro/raid/dens/common/data/raid/RaidCycleMode;)Lnet/minecraft/resources/ResourceLocation;
      14: goto          21
      17: aload_0
      18: getfield      #136                // Field raidBoss:Lnet/minecraft/resources/ResourceLocation;
      21: areturn

  public boolean spawnRaidBoss(java.util.UUID);
    Code:
       0: aload_0
       1: invokevirtual #220                // Method getLevel:()Lnet/minecraft/world/level/Level;
       4: ifnonnull     9
       7: iconst_0
       8: ireturn
       9: aload_0
      10: invokevirtual #428                // Method getRaidBoss:()Lcom/necro/raid/dens/common/data/raid/RaidBoss;
      13: astore_2
      14: aload_0
      15: invokevirtual #120                // Method getUuid:()Ljava/util/UUID;
      18: invokestatic  #434                // Method com/necro/raid/dens/common/raids/helpers/RaidRegionHelper.getRegion:(Ljava/util/UUID;)Lcom/necro/raid/dens/common/data/dimension/RaidRegion;
      21: astore_3
      22: aload_0
      23: invokevirtual #220                // Method getLevel:()Lnet/minecraft/world/level/Level;
      26: invokevirtual #438                // Method net/minecraft/world/level/Level.getServer:()Lnet/minecraft/server/MinecraftServer;
      29: invokestatic  #444                // Method com/necro/raid/dens/common/dimensions/ModDimensions.getRaidDimension:(Lnet/minecraft/server/MinecraftServer;)Lnet/minecraft/server/level/ServerLevel;
      32: astore        4
      34: aload_2
      35: ifnull        47
      38: aload_3
      39: ifnull        47
      42: aload         4
      44: ifnonnull     70
      47: getstatic     #450                // Field com/necro/raid/dens/common/CobblemonRaidDens.LOGGER:Lorg/slf4j/Logger;
      50: ldc_w         #452                // String Could not load Raid Boss {}
      53: aload_0
      54: getfield      #136                // Field raidBoss:Lnet/minecraft/resources/ResourceLocation;
      57: invokeinterface #458,  3          // InterfaceMethod org/slf4j/Logger.error:(Ljava/lang/String;Ljava/lang/Object;)V
      62: aload_0
      63: aconst_null
      64: lconst_0
      65: invokevirtual #329                // Method setRaidBoss:(Lnet/minecraft/resources/ResourceLocation;J)V
      68: iconst_0
      69: ireturn
      70: aload_3
      71: aload         4
      73: invokevirtual #462                // Method com/necro/raid/dens/common/data/dimension/RaidRegion.placeStructure:(Lnet/minecraft/server/level/ServerLevel;)V
      76: aload_2
      77: aload         4
      79: aload_0
      80: getfield      #464                // Field aspects:Ljava/util/Set;
      83: invokevirtual #468                // Method com/necro/raid/dens/common/data/raid/RaidBoss.getBossEntity:(Lnet/minecraft/server/level/ServerLevel;Ljava/util/Set;)Lcom/cobblemon/mod/common/entity/pokemon/PokemonEntity;
      86: astore        5
      88: goto          112
      91: astore        6
      93: getstatic     #450                // Field com/necro/raid/dens/common/CobblemonRaidDens.LOGGER:Lorg/slf4j/Logger;
      96: ldc_w         #470                // String Failed to parse raid boss {}:
      99: aload_0
     100: getfield      #136                // Field raidBoss:Lnet/minecraft/resources/ResourceLocation;
     103: aload         6
     105: invokeinterface #473,  4          // InterfaceMethod org/slf4j/Logger.error:(Ljava/lang/String;Ljava/lang/Object;Ljava/lang/Object;)V
     110: iconst_0
     111: ireturn
     112: aload_2
     113: invokevirtual #479                // Method com/necro/raid/dens/common/data/raid/RaidBoss.getNoAi:()Ljava/lang/Boolean;
     116: invokevirtual #187                // Method java/lang/Boolean.booleanValue:()Z
     119: ifeq          128
     122: aload         5
     124: iconst_1
     125: invokevirtual #483                // Method com/cobblemon/mod/common/entity/pokemon/PokemonEntity.setNoAi:(Z)V
     128: aload         5
     130: iconst_1
     131: invokevirtual #486                // Method com/cobblemon/mod/common/entity/pokemon/PokemonEntity.setInvulnerable:(Z)V
     134: aload         5
     136: invokevirtual #489                // Method com/cobblemon/mod/common/entity/pokemon/PokemonEntity.setPersistenceRequired:()V
     139: aload         5
     141: checkcast     #491                // class com/necro/raid/dens/common/util/IRaidAccessor
     144: aload_0
     145: invokevirtual #120                // Method getUuid:()Ljava/util/UUID;
     148: invokeinterface #495,  2          // InterfaceMethod com/necro/raid/dens/common/util/IRaidAccessor.crd_setRaidId:(Ljava/util/UUID;)V
     153: getstatic     #193                // Field com/necro/raid/dens/common/CobblemonRaidDens.CONFIG:Lcom/necro/raid/dens/common/config/RaidConfig;
     156: getfield      #498                // Field com/necro/raid/dens/common/config/RaidConfig.sync_rewards:Z
     159: ifeq          182
     162: aload_0
     163: getfield      #464                // Field aspects:Ljava/util/Set;
     166: ifnonnull     182
     169: aload_0
     170: aload         5
     172: invokevirtual #502                // Method com/cobblemon/mod/common/entity/pokemon/PokemonEntity.getAspects:()Ljava/util/Set;
     175: putfield      #464                // Field aspects:Ljava/util/Set;
     178: aload_0
     179: invokevirtual #505                // Method setChanged:()V
     182: new           #507                // class com/necro/raid/dens/common/raids/RaidInstance
     185: dup
     186: aload         5
     188: aload_1
     189: invokespecial #510                // Method com/necro/raid/dens/common/raids/RaidInstance."<init>":(Lcom/cobblemon/mod/common/entity/pokemon/PokemonEntity;Ljava/util/UUID;)V
     192: astore        6
     194: aload         6
     196: invokevirtual #513                // Method com/necro/raid/dens/common/raids/RaidInstance.failedToStart:()Z
     199: ifeq          204
     202: iconst_0
     203: ireturn
     204: getstatic     #517                // Field com/necro/raid/dens/common/raids/helpers/RaidHelper.ACTIVE_RAIDS:Ljava/util/Map;
     207: aload_0
     208: invokevirtual #120                // Method getUuid:()Ljava/util/UUID;
     211: aload         6
     213: invokeinterface #523,  3          // InterfaceMethod java/util/Map.put:(Ljava/lang/Object;Ljava/lang/Object;)Ljava/lang/Object;
     218: pop
     219: aload         5
     221: aload_3
     222: invokevirtual #527                // Method com/necro/raid/dens/common/data/dimension/RaidRegion.getBossPos:()Lnet/minecraft/world/phys/Vec3;
     225: invokevirtual #531                // Method com/cobblemon/mod/common/entity/pokemon/PokemonEntity.moveTo:(Lnet/minecraft/world/phys/Vec3;)V
     228: aload         4
     230: aload         5
     232: invokevirtual #535                // Method net/minecraft/server/level/ServerLevel.addFreshEntity:(Lnet/minecraft/world/entity/Entity;)Z
     235: pop
     236: aload         5
     238: invokevirtual #539                // Method com/cobblemon/mod/common/entity/pokemon/PokemonEntity.getPokemon:()Lcom/cobblemon/mod/common/pokemon/Pokemon;
     241: invokevirtual #545                // Method com/cobblemon/mod/common/pokemon/Pokemon.getAbility:()Lcom/cobblemon/mod/common/api/abilities/Ability;
     244: invokevirtual #551                // Method com/cobblemon/mod/common/api/abilities/Ability.getName:()Ljava/lang/String;
     247: ldc_w         #553                // String imposter
     250: invokevirtual #559                // Method java/lang/String.equals:(Ljava/lang/Object;)Z
     253: ifeq          267
     256: aload_0
     257: aload         5
     259: invokedynamic #579,  0            // InvokeDynamic #0:accept:(Lcom/cobblemon/mod/common/entity/pokemon/PokemonEntity;)Ljava/util/function/Consumer;
     264: invokevirtual #583                // Method setAspectSync:(Ljava/util/function/Consumer;)V
     267: iconst_1
     268: ireturn
    Exception table:
       from    to  target type
          76    88    91   Class java/lang/Exception

  public void clearRaid(boolean);
    Code:
       0: aload_0
       1: dup
       2: getfield      #596                // Field clears:I
       5: iconst_1
       6: iadd
       7: putfield      #596                // Field clears:I
      10: iload_1
      11: ifeq          23
      14: aload_0
      15: aconst_null
      16: putfield      #464                // Field aspects:Ljava/util/Set;
      19: aload_0
      20: invokevirtual #505                // Method setChanged:()V
      23: aload_0
      24: invokevirtual #599                // Method isAtMaxClears:()Z
      27: ifeq          74
      30: aload_0
      31: invokevirtual #120                // Method getUuid:()Ljava/util/UUID;
      34: invokestatic  #602                // Method com/necro/raid/dens/common/raids/helpers/RaidHelper.resetClearedRaids:(Ljava/util/UUID;)V
      37: aload_0
      38: invokevirtual #220                // Method getLevel:()Lnet/minecraft/world/level/Level;
      41: ifnull        74
      44: aload_0
      45: invokevirtual #220                // Method getLevel:()Lnet/minecraft/world/level/Level;
      48: aload_0
      49: invokevirtual #228                // Method getBlockPos:()Lnet/minecraft/core/BlockPos;
      52: aload_0
      53: invokevirtual #605                // Method getBlockState:()Lnet/minecraft/world/level/block/state/BlockState;
      56: getstatic     #350                // Field com/necro/raid/dens/common/blocks/block/RaidCrystalBlock.ACTIVE:Lnet/minecraft/world/level/block/state/properties/BooleanProperty;
      59: iconst_0
      60: invokestatic  #354                // Method java/lang/Boolean.valueOf:(Z)Ljava/lang/Boolean;
      63: invokevirtual #340                // Method net/minecraft/world/level/block/state/BlockState.setValue:(Lnet/minecraft/world/level/block/state/properties/Property;Ljava/lang/Comparable;)Ljava/lang/Object;
      66: checkcast     #178                // class net/minecraft/world/level/block/state/BlockState
      69: iconst_2
      70: invokevirtual #358                // Method net/minecraft/world/level/Level.setBlock:(Lnet/minecraft/core/BlockPos;Lnet/minecraft/world/level/block/state/BlockState;I)Z
      73: pop
      74: return

  private boolean shouldClear(com.necro.raid.dens.common.raids.RaidState);
    Code:
       0: aload_1
       1: ifnonnull     6
       4: iconst_0
       5: ireturn
       6: aload_1
       7: getstatic     #614                // Field com/necro/raid/dens/common/raids/RaidState.SUCCESS:Lcom/necro/raid/dens/common/raids/RaidState;
      10: if_acmpne     15
      13: iconst_1
      14: ireturn
      15: getstatic     #193                // Field com/necro/raid/dens/common/CobblemonRaidDens.CONFIG:Lcom/necro/raid/dens/common/config/RaidConfig;
      18: getfield      #617                // Field com/necro/raid/dens/common/config/RaidConfig.max_clears_include_fails:Z
      21: ifeq          35
      24: aload_1
      25: getstatic     #620                // Field com/necro/raid/dens/common/raids/RaidState.CANCELLED:Lcom/necro/raid/dens/common/raids/RaidState;
      28: if_acmpeq     35
      31: iconst_1
      32: goto          36
      35: iconst_0
      36: ireturn

  public void closeRaid();
    Code:
       0: aload_0
       1: invokevirtual #220                // Method getLevel:()Lnet/minecraft/world/level/Level;
       4: ifnonnull     8
       7: return
       8: aload_0
       9: invokevirtual #220                // Method getLevel:()Lnet/minecraft/world/level/Level;
      12: invokevirtual #438                // Method net/minecraft/world/level/Level.getServer:()Lnet/minecraft/server/MinecraftServer;
      15: invokestatic  #444                // Method com/necro/raid/dens/common/dimensions/ModDimensions.getRaidDimension:(Lnet/minecraft/server/MinecraftServer;)Lnet/minecraft/server/level/ServerLevel;
      18: astore_1
      19: aload_1
      20: ifnonnull     24
      23: return
      24: aload_0
      25: invokevirtual #120                // Method getUuid:()Ljava/util/UUID;
      28: invokestatic  #624                // Method com/necro/raid/dens/common/raids/helpers/RaidHelper.getRaidState:(Ljava/util/UUID;)Lcom/necro/raid/dens/common/raids/RaidState;
      31: astore_2
      32: aload_0
      33: aload_2
      34: invokevirtual #626                // Method shouldClear:(Lcom/necro/raid/dens/common/raids/RaidState;)Z
      37: ifeq          56
      40: aload_0
      41: aload_2
      42: getstatic     #614                // Field com/necro/raid/dens/common/raids/RaidState.SUCCESS:Lcom/necro/raid/dens/common/raids/RaidState;
      45: if_acmpne     52
      48: iconst_1
      49: goto          53
      52: iconst_0
      53: invokevirtual #628                // Method clearRaid:(Z)V
      56: aload_0
      57: invokevirtual #120                // Method getUuid:()Ljava/util/UUID;
      60: aload_1
      61: invokestatic  #632                // Method com/necro/raid/dens/common/raids/helpers/RaidRegionHelper.clearRegion:(Ljava/util/UUID;Lnet/minecraft/server/level/ServerLevel;)V
      64: aload_0
      65: iconst_0
      66: putfield      #150                // Field inactiveTicks:I
      69: aload_0
      70: invokevirtual #220                // Method getLevel:()Lnet/minecraft/world/level/Level;
      73: aload_0
      74: invokevirtual #228                // Method getBlockPos:()Lnet/minecraft/core/BlockPos;
      77: invokevirtual #636                // Method net/minecraft/world/level/Level.getChunkAt:(Lnet/minecraft/core/BlockPos;)Lnet/minecraft/world/level/chunk/LevelChunk;
      80: iconst_1
      81: invokevirtual #641                // Method net/minecraft/world/level/chunk/LevelChunk.setUnsaved:(Z)V
      84: aload_0
      85: invokevirtual #505                // Method setChanged:()V
      88: aload_0
      89: iconst_0
      90: putfield      #95                 // Field isOpen:Z
      93: aload_0
      94: aconst_null
      95: invokevirtual #583                // Method setAspectSync:(Ljava/util/function/Consumer;)V
      98: return

  public java.util.UUID getUuid();
    Code:
       0: aload_0
       1: getfield      #93                 // Field uuid:Ljava/util/UUID;
       4: areturn

  public com.necro.raid.dens.common.data.raid.RaidBucket getRaidBucket();
    Code:
       0: aload_0
       1: getfield      #375                // Field raidBucket:Lnet/minecraft/resources/ResourceLocation;
       4: invokestatic  #393                // Method com/necro/raid/dens/common/registry/RaidBucketRegistry.getBucket:(Lnet/minecraft/resources/ResourceLocation;)Lcom/necro/raid/dens/common/data/raid/RaidBucket;
       7: areturn

  public com.necro.raid.dens.common.data.raid.RaidBoss getRaidBoss();
    Code:
       0: aload_0
       1: getfield      #136                // Field raidBoss:Lnet/minecraft/resources/ResourceLocation;
       4: invokestatic  #299                // Method com/necro/raid/dens/common/registry/RaidRegistry.getRaidBoss:(Lnet/minecraft/resources/ResourceLocation;)Lcom/necro/raid/dens/common/data/raid/RaidBoss;
       7: areturn

  public net.minecraft.resources.ResourceLocation getRaidBossLocation();
    Code:
       0: aload_0
       1: getfield      #136                // Field raidBoss:Lnet/minecraft/resources/ResourceLocation;
       4: areturn

  public int getClears();
    Code:
       0: aload_0
       1: getfield      #596                // Field clears:I
       4: ireturn

  public int getPlayerCount();
    Code:
       0: getstatic     #517                // Field com/necro/raid/dens/common/raids/helpers/RaidHelper.ACTIVE_RAIDS:Ljava/util/Map;
       3: aload_0
       4: invokevirtual #120                // Method getUuid:()Ljava/util/UUID;
       7: invokeinterface #650,  2          // InterfaceMethod java/util/Map.get:(Ljava/lang/Object;)Ljava/lang/Object;
      12: checkcast     #507                // class com/necro/raid/dens/common/raids/RaidInstance
      15: astore_1
      16: aload_1
      17: ifnonnull     22
      20: iconst_0
      21: ireturn
      22: aload_1
      23: invokevirtual #652                // Method com/necro/raid/dens/common/raids/RaidInstance.getPlayerCount:()I
      26: ireturn

  public long getTicksUntilNextReset();
    Code:
       0: aload_0
       1: invokevirtual #220                // Method getLevel:()Lnet/minecraft/world/level/Level;
       4: ifnonnull     9
       7: lconst_0
       8: lreturn
       9: aload_0
      10: invokevirtual #605                // Method getBlockState:()Lnet/minecraft/world/level/block/state/BlockState;
      13: getstatic     #176                // Field com/necro/raid/dens/common/blocks/block/RaidCrystalBlock.CAN_RESET:Lnet/minecraft/world/level/block/state/properties/BooleanProperty;
      16: invokevirtual #182                // Method net/minecraft/world/level/block/state/BlockState.getValue:(Lnet/minecraft/world/level/block/state/properties/Property;)Ljava/lang/Comparable;
      19: checkcast     #184                // class java/lang/Boolean
      22: invokevirtual #187                // Method java/lang/Boolean.booleanValue:()Z
      25: ifne          30
      28: lconst_0
      29: lreturn
      30: getstatic     #193                // Field com/necro/raid/dens/common/CobblemonRaidDens.CONFIG:Lcom/necro/raid/dens/common/config/RaidConfig;
      33: getfield      #198                // Field com/necro/raid/dens/common/config/RaidConfig.reset_time:I
      36: ifgt          41
      39: lconst_0
      40: lreturn
      41: aload_0
      42: getfield      #204                // Field lastReset:Lcom/necro/raid/dens/common/data/raid/RaidResetContext;
      45: ifnonnull     50
      48: lconst_0
      49: lreturn
      50: aload_0
      51: getfield      #204                // Field lastReset:Lcom/necro/raid/dens/common/data/raid/RaidResetContext;
      54: aload_0
      55: invokevirtual #220                // Method getLevel:()Lnet/minecraft/world/level/Level;
      58: invokevirtual #202                // Method net/minecraft/world/level/Level.getGameTime:()J
      61: invokevirtual #657                // Method com/necro/raid/dens/common/data/raid/RaidResetContext.nextReset:(J)J
      64: lreturn

  public boolean isOpen();
    Code:
       0: aload_0
       1: getfield      #95                 // Field isOpen:Z
       4: ireturn

  public void setUuid(java.util.UUID);
    Code:
       0: aload_0
       1: aload_1
       2: putfield      #93                 // Field uuid:Ljava/util/UUID;
       5: return

  public void setRaidBucket(net.minecraft.resources.ResourceLocation);
    Code:
       0: aload_0
       1: aload_1
       2: putfield      #375                // Field raidBucket:Lnet/minecraft/resources/ResourceLocation;
       5: return

  public void setRaidBoss(net.minecraft.resources.ResourceLocation, long);
    Code:
       0: aload_0
       1: invokevirtual #120                // Method getUuid:()Ljava/util/UUID;
       4: invokestatic  #602                // Method com/necro/raid/dens/common/raids/helpers/RaidHelper.resetClearedRaids:(Ljava/util/UUID;)V
       7: aload_0
       8: invokevirtual #663                // Method resetClears:()V
      11: aload_0
      12: iconst_0
      13: putfield      #150                // Field inactiveTicks:I
      16: aload_0
      17: new           #206                // class com/necro/raid/dens/common/data/raid/RaidResetContext
      20: dup
      21: lload_2
      22: invokespecial #209                // Method com/necro/raid/dens/common/data/raid/RaidResetContext."<init>":(J)V
      25: putfield      #204                // Field lastReset:Lcom/necro/raid/dens/common/data/raid/RaidResetContext;
      28: aload_0
      29: aload_1
      30: putfield      #136                // Field raidBoss:Lnet/minecraft/resources/ResourceLocation;
      33: aload_0
      34: aconst_null
      35: putfield      #464                // Field aspects:Ljava/util/Set;
      38: aload_0
      39: invokevirtual #505                // Method setChanged:()V
      42: aload_0
      43: invokevirtual #220                // Method getLevel:()Lnet/minecraft/world/level/Level;
      46: ifnull        69
      49: aload_0
      50: invokevirtual #220                // Method getLevel:()Lnet/minecraft/world/level/Level;
      53: aload_0
      54: invokevirtual #228                // Method getBlockPos:()Lnet/minecraft/core/BlockPos;
      57: aload_0
      58: invokevirtual #605                // Method getBlockState:()Lnet/minecraft/world/level/block/state/BlockState;
      61: aload_0
      62: invokevirtual #605                // Method getBlockState:()Lnet/minecraft/world/level/block/state/BlockState;
      65: iconst_3
      66: invokevirtual #667                // Method net/minecraft/world/level/Level.sendBlockUpdated:(Lnet/minecraft/core/BlockPos;Lnet/minecraft/world/level/block/state/BlockState;Lnet/minecraft/world/level/block/state/BlockState;I)V
      69: return

  public void setClears(int);
    Code:
       0: aload_0
       1: iload_1
       2: putfield      #596                // Field clears:I
       5: return

  public void setOpen();
    Code:
       0: aload_0
       1: iconst_1
       2: putfield      #95                 // Field isOpen:Z
       5: return

  public boolean isPlayerParticipating(net.minecraft.world.entity.player.Player);
    Code:
       0: aload_1
       1: aload_0
       2: invokevirtual #120                // Method getUuid:()Ljava/util/UUID;
       5: invokestatic  #679                // Method com/necro/raid/dens/common/raids/helpers/RaidJoinHelper.isParticipating:(Lnet/minecraft/world/entity/player/Player;Ljava/util/UUID;)Z
       8: ireturn

  public boolean isInProgress();
    Code:
       0: getstatic     #517                // Field com/necro/raid/dens/common/raids/helpers/RaidHelper.ACTIVE_RAIDS:Ljava/util/Map;
       3: aload_0
       4: invokevirtual #120                // Method getUuid:()Ljava/util/UUID;
       7: invokeinterface #683,  2          // InterfaceMethod java/util/Map.containsKey:(Ljava/lang/Object;)Z
      12: ireturn

  public boolean isIdle();
    Code:
       0: aload_0
       1: invokevirtual #220                // Method getLevel:()Lnet/minecraft/world/level/Level;
       4: ifnonnull     9
       7: iconst_0
       8: ireturn
       9: aload_0
      10: invokevirtual #120                // Method getUuid:()Ljava/util/UUID;
      13: invokestatic  #434                // Method com/necro/raid/dens/common/raids/helpers/RaidRegionHelper.getRegion:(Ljava/util/UUID;)Lcom/necro/raid/dens/common/data/dimension/RaidRegion;
      16: astore_1
      17: aload_1
      18: ifnonnull     23
      21: iconst_1
      22: ireturn
      23: aload_0
      24: invokevirtual #220                // Method getLevel:()Lnet/minecraft/world/level/Level;
      27: invokevirtual #438                // Method net/minecraft/world/level/Level.getServer:()Lnet/minecraft/server/MinecraftServer;
      30: invokestatic  #444                // Method com/necro/raid/dens/common/dimensions/ModDimensions.getRaidDimension:(Lnet/minecraft/server/MinecraftServer;)Lnet/minecraft/server/level/ServerLevel;
      33: astore_2
      34: aload_2
      35: ifnonnull     40
      38: iconst_0
      39: ireturn
      40: aload_2
      41: ldc_w         #685                // class net/minecraft/world/entity/player/Player
      44: aload_1
      45: invokevirtual #689                // Method com/necro/raid/dens/common/data/dimension/RaidRegion.bound:()Lnet/minecraft/world/phys/AABB;
      48: invokevirtual #693                // Method net/minecraft/server/level/ServerLevel.getEntitiesOfClass:(Ljava/lang/Class;Lnet/minecraft/world/phys/AABB;)Ljava/util/List;
      51: invokeinterface #698,  1          // InterfaceMethod java/util/List.size:()I
      56: istore_3
      57: iload_3
      58: ifne          65
      61: iconst_1
      62: goto          66
      65: iconst_0
      66: ireturn

  public boolean isActive(net.minecraft.world.level.block.state.BlockState);
    Code:
       0: aload_1
       1: getstatic     #350                // Field com/necro/raid/dens/common/blocks/block/RaidCrystalBlock.ACTIVE:Lnet/minecraft/world/level/block/state/properties/BooleanProperty;
       4: invokevirtual #182                // Method net/minecraft/world/level/block/state/BlockState.getValue:(Lnet/minecraft/world/level/block/state/properties/Property;)Ljava/lang/Comparable;
       7: checkcast     #184                // class java/lang/Boolean
      10: invokevirtual #187                // Method java/lang/Boolean.booleanValue:()Z
      13: ifeq          40
      16: aload_1
      17: getstatic     #343                // Field com/necro/raid/dens/common/blocks/block/RaidCrystalBlock.RAID_TYPE:Lnet/minecraft/world/level/block/state/properties/EnumProperty;
      20: invokevirtual #182                // Method net/minecraft/world/level/block/state/BlockState.getValue:(Lnet/minecraft/world/level/block/state/properties/Property;)Ljava/lang/Comparable;
      23: getstatic     #702                // Field com/necro/raid/dens/common/data/raid/RaidType.NONE:Lcom/necro/raid/dens/common/data/raid/RaidType;
      26: if_acmpeq     40
      29: aload_0
      30: getfield      #136                // Field raidBoss:Lnet/minecraft/resources/ResourceLocation;
      33: ifnull        40
      36: iconst_1
      37: goto          41
      40: iconst_0
      41: ireturn

  public boolean canGenerateBoss(net.minecraft.world.level.block.state.BlockState);
    Code:
       0: aload_1
       1: getstatic     #350                // Field com/necro/raid/dens/common/blocks/block/RaidCrystalBlock.ACTIVE:Lnet/minecraft/world/level/block/state/properties/BooleanProperty;
       4: invokevirtual #182                // Method net/minecraft/world/level/block/state/BlockState.getValue:(Lnet/minecraft/world/level/block/state/properties/Property;)Ljava/lang/Comparable;
       7: checkcast     #184                // class java/lang/Boolean
      10: invokevirtual #187                // Method java/lang/Boolean.booleanValue:()Z
      13: ifeq          33
      16: aload_1
      17: getstatic     #343                // Field com/necro/raid/dens/common/blocks/block/RaidCrystalBlock.RAID_TYPE:Lnet/minecraft/world/level/block/state/properties/EnumProperty;
      20: invokevirtual #182                // Method net/minecraft/world/level/block/state/BlockState.getValue:(Lnet/minecraft/world/level/block/state/properties/Property;)Ljava/lang/Comparable;
      23: getstatic     #702                // Field com/necro/raid/dens/common/data/raid/RaidType.NONE:Lcom/necro/raid/dens/common/data/raid/RaidType;
      26: if_acmpeq     33
      29: iconst_1
      30: goto          34
      33: iconst_0
      34: ireturn

  public void resetClears();
    Code:
       0: aload_0
       1: iconst_0
       2: putfield      #596                // Field clears:I
       5: return

  public boolean isAtMaxClears();
    Code:
       0: aload_0
       1: invokevirtual #428                // Method getRaidBoss:()Lcom/necro/raid/dens/common/data/raid/RaidBoss;
       4: astore_1
       5: aload_1
       6: ifnonnull     11
       9: iconst_1
      10: ireturn
      11: aload_1
      12: invokevirtual #706                // Method com/necro/raid/dens/common/data/raid/RaidBoss.getMaxClears:()Ljava/lang/Integer;
      15: invokevirtual #711                // Method java/lang/Integer.intValue:()I
      18: istore_2
      19: iload_2
      20: iconst_m1
      21: if_icmpeq     36
      24: aload_0
      25: getfield      #596                // Field clears:I
      28: iload_2
      29: if_icmplt     36
      32: iconst_1
      33: goto          37
      36: iconst_0
      37: ireturn

  public boolean isFull();
    Code:
       0: aload_0
       1: invokevirtual #428                // Method getRaidBoss:()Lcom/necro/raid/dens/common/data/raid/RaidBoss;
       4: astore_1
       5: aload_1
       6: ifnonnull     11
       9: iconst_1
      10: ireturn
      11: aload_1
      12: invokevirtual #716                // Method com/necro/raid/dens/common/data/raid/RaidBoss.getMaxPlayers:()Ljava/lang/Integer;
      15: invokevirtual #711                // Method java/lang/Integer.intValue:()I
      18: istore_2
      19: iload_2
      20: iconst_m1
      21: if_icmpeq     36
      24: aload_0
      25: invokevirtual #717                // Method getPlayerCount:()I
      28: iload_2
      29: if_icmplt     36
      32: iconst_1
      33: goto          37
      36: iconst_0
      37: ireturn

  public void syncAspects(net.minecraft.server.level.ServerPlayer);
    Code:
       0: aload_0
       1: getfield      #721                // Field aspectSync:Ljava/util/function/Consumer;
       4: ifnonnull     8
       7: return
       8: lconst_1
       9: getstatic     #727                // Field java/util/concurrent/TimeUnit.SECONDS:Ljava/util/concurrent/TimeUnit;
      12: invokestatic  #733                // Method java/util/concurrent/CompletableFuture.delayedExecutor:(JLjava/util/concurrent/TimeUnit;)Ljava/util/concurrent/Executor;
      15: aload_0
      16: aload_1
      17: invokedynamic #742,  0            // InvokeDynamic #1:run:(Lcom/necro/raid/dens/common/blocks/entity/RaidCrystalBlockEntity;Lnet/minecraft/server/level/ServerPlayer;)Ljava/lang/Runnable;
      22: invokeinterface #748,  2          // InterfaceMethod java/util/concurrent/Executor.execute:(Ljava/lang/Runnable;)V
      27: return

  public void setAspectSync(java.util.function.Consumer<net.minecraft.server.level.ServerPlayer>);
    Code:
       0: aload_0
       1: aload_1
       2: putfield      #721                // Field aspectSync:Ljava/util/function/Consumer;
       5: return

  protected void loadAdditional(net.minecraft.nbt.CompoundTag, net.minecraft.core.HolderLookup$Provider);
    Code:
       0: aload_0
       1: aload_1
       2: ldc_w         #758                // String raid_cleared
       5: invokevirtual #764                // Method net/minecraft/nbt/CompoundTag.getInt:(Ljava/lang/String;)I
       8: putfield      #596                // Field clears:I
      11: aload_0
      12: aload_1
      13: ldc_w         #766                // String reset_context
      16: invokevirtual #770                // Method net/minecraft/nbt/CompoundTag.getCompound:(Ljava/lang/String;)Lnet/minecraft/nbt/CompoundTag;
      19: invokestatic  #774                // Method com/necro/raid/dens/common/data/raid/RaidResetContext.load:(Lnet/minecraft/nbt/CompoundTag;)Lcom/necro/raid/dens/common/data/raid/RaidResetContext;
      22: putfield      #204                // Field lastReset:Lcom/necro/raid/dens/common/data/raid/RaidResetContext;
      25: aload_1
      26: ldc_w         #775                // String uuid
      29: invokevirtual #779                // Method net/minecraft/nbt/CompoundTag.contains:(Ljava/lang/String;)Z
      32: ifeq          52
      35: aload_0
      36: aload_1
      37: ldc_w         #775                // String uuid
      40: invokevirtual #783                // Method net/minecraft/nbt/CompoundTag.getString:(Ljava/lang/String;)Ljava/lang/String;
      43: invokestatic  #787                // Method java/util/UUID.fromString:(Ljava/lang/String;)Ljava/util/UUID;
      46: putfield      #93                 // Field uuid:Ljava/util/UUID;
      49: goto          59
      52: aload_0
      53: invokestatic  #91                 // Method java/util/UUID.randomUUID:()Ljava/util/UUID;
      56: putfield      #93                 // Field uuid:Ljava/util/UUID;
      59: aload_1
      60: ldc_w         #789                // String raid_bucket
      63: invokevirtual #779                // Method net/minecraft/nbt/CompoundTag.contains:(Ljava/lang/String;)Z
      66: ifeq          83
      69: aload_0
      70: aload_1
      71: ldc_w         #789                // String raid_bucket
      74: invokevirtual #783                // Method net/minecraft/nbt/CompoundTag.getString:(Ljava/lang/String;)Ljava/lang/String;
      77: invokestatic  #793                // Method net/minecraft/resources/ResourceLocation.parse:(Ljava/lang/String;)Lnet/minecraft/resources/ResourceLocation;
      80: putfield      #375                // Field raidBucket:Lnet/minecraft/resources/ResourceLocation;
      83: aload_1
      84: ldc_w         #795                // String raid_boss
      87: invokevirtual #779                // Method net/minecraft/nbt/CompoundTag.contains:(Ljava/lang/String;)Z
      90: ifeq          107
      93: aload_0
      94: aload_1
      95: ldc_w         #795                // String raid_boss
      98: invokevirtual #783                // Method net/minecraft/nbt/CompoundTag.getString:(Ljava/lang/String;)Ljava/lang/String;
     101: invokestatic  #793                // Method net/minecraft/resources/ResourceLocation.parse:(Ljava/lang/String;)Lnet/minecraft/resources/ResourceLocation;
     104: putfield      #136                // Field raidBoss:Lnet/minecraft/resources/ResourceLocation;
     107: aload_1
     108: ldc_w         #797                // String is_open
     111: invokevirtual #779                // Method net/minecraft/nbt/CompoundTag.contains:(Ljava/lang/String;)Z
     114: ifeq          122
     117: aload_0
     118: iconst_1
     119: putfield      #95                 // Field isOpen:Z
     122: aload_1
     123: ldc_w         #798                // String aspects
     126: invokevirtual #779                // Method net/minecraft/nbt/CompoundTag.contains:(Ljava/lang/String;)Z
     129: ifeq          198
     132: new           #800                // class java/util/HashSet
     135: dup
     136: invokespecial #802                // Method java/util/HashSet."<init>":()V
     139: astore_3
     140: aload_1
     141: ldc_w         #798                // String aspects
     144: bipush        8
     146: invokevirtual #806                // Method net/minecraft/nbt/CompoundTag.getList:(Ljava/lang/String;I)Lnet/minecraft/nbt/ListTag;
     149: invokevirtual #812                // Method net/minecraft/nbt/ListTag.iterator:()Ljava/util/Iterator;
     152: astore        4
     154: aload         4
     156: invokeinterface #817,  1          // InterfaceMethod java/util/Iterator.hasNext:()Z
     161: ifeq          193
     164: aload         4
     166: invokeinterface #821,  1          // InterfaceMethod java/util/Iterator.next:()Ljava/lang/Object;
     171: checkcast     #823                // class net/minecraft/nbt/Tag
     174: astore        5
     176: aload_3
     177: aload         5
     179: invokeinterface #826,  1          // InterfaceMethod net/minecraft/nbt/Tag.getAsString:()Ljava/lang/String;
     184: invokeinterface #831,  2          // InterfaceMethod java/util/Set.add:(Ljava/lang/Object;)Z
     189: pop
     190: goto          154
     193: aload_0
     194: aload_3
     195: putfield      #464                // Field aspects:Ljava/util/Set;
     198: return

  protected void saveAdditional(net.minecraft.nbt.CompoundTag, net.minecraft.core.HolderLookup$Provider);
    Code:
       0: aload_1
       1: ldc_w         #758                // String raid_cleared
       4: aload_0
       5: getfield      #596                // Field clears:I
       8: invokevirtual #840                // Method net/minecraft/nbt/CompoundTag.putInt:(Ljava/lang/String;I)V
      11: aload_0
      12: getfield      #204                // Field lastReset:Lcom/necro/raid/dens/common/data/raid/RaidResetContext;
      15: ifnull        40
      18: aload_1
      19: ldc_w         #766                // String reset_context
      22: aload_0
      23: getfield      #204                // Field lastReset:Lcom/necro/raid/dens/common/data/raid/RaidResetContext;
      26: new           #760                // class net/minecraft/nbt/CompoundTag
      29: dup
      30: invokespecial #841                // Method net/minecraft/nbt/CompoundTag."<init>":()V
      33: invokevirtual #845                // Method com/necro/raid/dens/common/data/raid/RaidResetContext.save:(Lnet/minecraft/nbt/CompoundTag;)Lnet/minecraft/nbt/CompoundTag;
      36: invokevirtual #848                // Method net/minecraft/nbt/CompoundTag.put:(Ljava/lang/String;Lnet/minecraft/nbt/Tag;)Lnet/minecraft/nbt/Tag;
      39: pop
      40: aload_0
      41: getfield      #93                 // Field uuid:Ljava/util/UUID;
      44: ifnull        61
      47: aload_1
      48: ldc_w         #775                // String uuid
      51: aload_0
      52: getfield      #93                 // Field uuid:Ljava/util/UUID;
      55: invokevirtual #851                // Method java/util/UUID.toString:()Ljava/lang/String;
      58: invokevirtual #855                // Method net/minecraft/nbt/CompoundTag.putString:(Ljava/lang/String;Ljava/lang/String;)V
      61: aload_0
      62: getfield      #375                // Field raidBucket:Lnet/minecraft/resources/ResourceLocation;
      65: ifnull        82
      68: aload_1
      69: ldc_w         #789                // String raid_bucket
      72: aload_0
      73: getfield      #375                // Field raidBucket:Lnet/minecraft/resources/ResourceLocation;
      76: invokevirtual #856                // Method net/minecraft/resources/ResourceLocation.toString:()Ljava/lang/String;
      79: invokevirtual #855                // Method net/minecraft/nbt/CompoundTag.putString:(Ljava/lang/String;Ljava/lang/String;)V
      82: aload_0
      83: getfield      #136                // Field raidBoss:Lnet/minecraft/resources/ResourceLocation;
      86: ifnull        103
      89: aload_1
      90: ldc_w         #795                // String raid_boss
      93: aload_0
      94: getfield      #136                // Field raidBoss:Lnet/minecraft/resources/ResourceLocation;
      97: invokevirtual #856                // Method net/minecraft/resources/ResourceLocation.toString:()Ljava/lang/String;
     100: invokevirtual #855                // Method net/minecraft/nbt/CompoundTag.putString:(Ljava/lang/String;Ljava/lang/String;)V
     103: aload_0
     104: getfield      #95                 // Field isOpen:Z
     107: ifeq          118
     110: aload_1
     111: ldc_w         #797                // String is_open
     114: iconst_1
     115: invokevirtual #860                // Method net/minecraft/nbt/CompoundTag.putBoolean:(Ljava/lang/String;Z)V
     118: aload_0
     119: getfield      #464                // Field aspects:Ljava/util/Set;
     122: ifnull        157
     125: new           #808                // class net/minecraft/nbt/ListTag
     128: dup
     129: invokespecial #861                // Method net/minecraft/nbt/ListTag."<init>":()V
     132: astore_3
     133: aload_0
     134: getfield      #464                // Field aspects:Ljava/util/Set;
     137: aload_3
     138: invokedynamic #871,  0            // InvokeDynamic #2:accept:(Lnet/minecraft/nbt/ListTag;)Ljava/util/function/Consumer;
     143: invokeinterface #874,  2          // InterfaceMethod java/util/Set.forEach:(Ljava/util/function/Consumer;)V
     148: aload_1
     149: ldc_w         #798                // String aspects
     152: aload_3
     153: invokevirtual #848                // Method net/minecraft/nbt/CompoundTag.put:(Ljava/lang/String;Lnet/minecraft/nbt/Tag;)Lnet/minecraft/nbt/Tag;
     156: pop
     157: return

  public net.minecraft.nbt.CompoundTag getUpdateTag(net.minecraft.core.HolderLookup$Provider);
    Code:
       0: aload_0
       1: aload_1
       2: invokespecial #879                // Method net/minecraft/world/level/block/entity/BlockEntity.getUpdateTag:(Lnet/minecraft/core/HolderLookup$Provider;)Lnet/minecraft/nbt/CompoundTag;
       5: astore_2
       6: aload_0
       7: getfield      #136                // Field raidBoss:Lnet/minecraft/resources/ResourceLocation;
      10: ifnull        27
      13: aload_2
      14: ldc_w         #795                // String raid_boss
      17: aload_0
      18: getfield      #136                // Field raidBoss:Lnet/minecraft/resources/ResourceLocation;
      21: invokevirtual #856                // Method net/minecraft/resources/ResourceLocation.toString:()Ljava/lang/String;
      24: invokevirtual #855                // Method net/minecraft/nbt/CompoundTag.putString:(Ljava/lang/String;Ljava/lang/String;)V
      27: aload_2
      28: areturn

  public net.minecraft.network.protocol.Packet<net.minecraft.network.protocol.game.ClientGamePacketListener> getUpdatePacket();
    Code:
       0: aload_0
       1: invokestatic  #888                // Method net/minecraft/network/protocol/game/ClientboundBlockEntityDataPacket.create:(Lnet/minecraft/world/level/block/entity/BlockEntity;)Lnet/minecraft/network/protocol/game/ClientboundBlockEntityDataPacket;
       4: areturn

  public void registerControllers(software.bernie.geckolib.animation.AnimatableManager$ControllerRegistrar);
    Code:
       0: aload_1
       1: new           #23                 // class software/bernie/geckolib/animation/AnimationController
       4: dup
       5: aload_0
       6: ldc_w         #893                // String controller
       9: invokedynamic #903,  0            // InvokeDynamic #3:handle:()Lsoftware/bernie/geckolib/animation/AnimationController$AnimationStateHandler;
      14: invokespecial #906                // Method software/bernie/geckolib/animation/AnimationController."<init>":(Lsoftware/bernie/geckolib/animatable/GeoAnimatable;Ljava/lang/String;Lsoftware/bernie/geckolib/animation/AnimationController$AnimationStateHandler;)V
      17: aload_0
      18: invokedynamic #915,  0            // InvokeDynamic #4:handle:(Lcom/necro/raid/dens/common/blocks/entity/RaidCrystalBlockEntity;)Lsoftware/bernie/geckolib/animation/AnimationController$CustomKeyframeHandler;
      23: invokevirtual #919                // Method software/bernie/geckolib/animation/AnimationController.setCustomInstructionKeyframeHandler:(Lsoftware/bernie/geckolib/animation/AnimationController$CustomKeyframeHandler;)Lsoftware/bernie/geckolib/animation/AnimationController;
      26: invokevirtual #922                // Method software/bernie/geckolib/animation/AnimatableManager$ControllerRegistrar.add:(Lsoftware/bernie/geckolib/animation/AnimationController;)Lsoftware/bernie/geckolib/animation/AnimatableManager$ControllerRegistrar;
      29: pop
      30: return

  public software.bernie.geckolib.animatable.instance.AnimatableInstanceCache getAnimatableInstanceCache();
    Code:
       0: aload_0
       1: getfield      #77                 // Field cache:Lsoftware/bernie/geckolib/animatable/instance/AnimatableInstanceCache;
       4: areturn

  private void lambda$registerControllers$4(software.bernie.geckolib.animation.keyframe.event.CustomInstructionKeyframeEvent);
    Code:
       0: aload_1
       1: invokevirtual #931                // Method software/bernie/geckolib/animation/keyframe/event/CustomInstructionKeyframeEvent.getAnimatable:()Lsoftware/bernie/geckolib/animatable/GeoAnimatable;
       4: checkcast     #2                  // class com/necro/raid/dens/common/blocks/entity/RaidCrystalBlockEntity
       7: astore_2
       8: getstatic     #937                // Field com/necro/raid/dens/common/CobblemonRaidDensClient.CLIENT_CONFIG:Lcom/necro/raid/dens/common/config/ClientConfig;
      11: getfield      #942                // Field com/necro/raid/dens/common/config/ClientConfig.show_particles:Z
      14: ifne          18
      17: return
      18: aload_2
      19: aload_2
      20: invokevirtual #605                // Method getBlockState:()Lnet/minecraft/world/level/block/state/BlockState;
      23: invokevirtual #153                // Method isActive:(Lnet/minecraft/world/level/block/state/BlockState;)Z
      26: ifne          30
      29: return
      30: aload_2
      31: aload_2
      32: invokevirtual #605                // Method getBlockState:()Lnet/minecraft/world/level/block/state/BlockState;
      35: invokevirtual #134                // Method canGenerateBoss:(Lnet/minecraft/world/level/block/state/BlockState;)Z
      38: ifne          42
      41: return
      42: aload_0
      43: invokestatic  #948                // Method com/necro/raid/dens/common/client/block/RaidCrystalSparkleRenderer.sparkle:(Lcom/necro/raid/dens/common/blocks/entity/RaidCrystalBlockEntity;)V
      46: return

  private static software.bernie.geckolib.animation.PlayState lambda$registerControllers$3(software.bernie.geckolib.animation.AnimationState);
    Code:
       0: aload_0
       1: invokestatic  #957                // Method software/bernie/geckolib/animation/RawAnimation.begin:()Lsoftware/bernie/geckolib/animation/RawAnimation;
       4: ldc_w         #959                // String animation.raid_den.sparkle
       7: invokevirtual #963                // Method software/bernie/geckolib/animation/RawAnimation.thenLoop:(Ljava/lang/String;)Lsoftware/bernie/geckolib/animation/RawAnimation;
      10: invokevirtual #969                // Method software/bernie/geckolib/animation/AnimationState.setAndContinue:(Lsoftware/bernie/geckolib/animation/RawAnimation;)Lsoftware/bernie/geckolib/animation/PlayState;
      13: areturn

  private static void lambda$saveAdditional$2(net.minecraft.nbt.ListTag, java.lang.String);
    Code:
       0: aload_0
       1: aload_1
       2: invokestatic  #976                // Method net/minecraft/nbt/StringTag.valueOf:(Ljava/lang/String;)Lnet/minecraft/nbt/StringTag;
       5: invokevirtual #977                // Method net/minecraft/nbt/ListTag.add:(Ljava/lang/Object;)Z
       8: pop
       9: return

  private void lambda$syncAspects$1(net.minecraft.server.level.ServerPlayer);
    Code:
       0: aload_0
       1: getfield      #721                // Field aspectSync:Ljava/util/function/Consumer;
       4: aload_1
       5: invokeinterface #982,  2          // InterfaceMethod java/util/function/Consumer.accept:(Ljava/lang/Object;)V
      10: return

  private static void lambda$spawnRaidBoss$0(com.cobblemon.mod.common.entity.pokemon.PokemonEntity, net.minecraft.server.level.ServerPlayer);
    Code:
       0: getstatic     #988                // Field com/necro/raid/dens/common/network/RaidDenNetworkMessages.RAID_ASPECT:Ljava/util/function/BiConsumer;
       3: aload_1
       4: aload_0
       5: invokeinterface #993,  3          // InterfaceMethod java/util/function/BiConsumer.accept:(Ljava/lang/Object;Ljava/lang/Object;)V
      10: return
}
